PyCliProg-0.3.0.dist-info/DESCRIPTION.rst
PyCliProg-0.3.0.dist-info/LICENSE.txt
PyCliProg-0.3.0.dist-info/METADATA
PyCliProg-0.3.0.dist-info/RECORD
PyCliProg-0.3.0.dist-info/WHEEL
PyCliProg-0.3.0.dist-info/metadata.json
PyCliProg-0.3.0.dist-info/top_level.txt
pycliprog/VERSION.txt
pycliprog/__init__.py
pycliprog/argparse/__init__.py
pycliprog/argparse/__main__.py
