Metadata-Version: 2.0
Name: PyCliProg
Version: 0.3.0
Summary: A minimal-complete Python command-line program.
Home-page: https://gitlab.com/imtheforce/pycliprog
Author: Gu Zhengxiong
Author-email: rectigu@gmail.com
License: Apache License Version 2.0
Keywords: command-line program
Platform: UNKNOWN
